labs/lab_03/summator.v
module summator(input a, input b, input c, output s, output h_c);

// проміжні дроти
wire xor1_out, and1_out, xor2_out, and2_out, or_out;

// 1 крок
xor xor1(xor1_out, a, b);
and and1(and1_out, a, b);

// 2 крок
xor xor2(xor2_out, xor1_out, c);
and and2(and2_out, xor1_out, c);

// 3 крок
or or1(or_out, and2_out, and1_out);
assign h_c = or_out;
assign s = xor2_out;

endmodule

/*
1 bit summator
------------------------------
| A | B | C_in | Sum | C_out | 
| 0 | 0 | 0    | 0   | 0     |
| 0 | 0 | 1    | 1   | 0     | 
| 0 | 1 | 0    | 1   | 0     | 
| 0 | 1 | 1    | 0   | 1     |
| 1 | 0 | 0    | 1   | 0     |
| 1 | 0 | 1    | 0   | 1     |
| 1 | 1 | 0    | 0   | 1     |
| 1 | 1 | 1    | 1   | 1     |
*/

labs/lab_03/summator_tb.v
`timescale 1ns / 1ns

module summator_tb;
    reg a;
    reg b;
    reg c;
    wire s;
    wire h_c;

    integer i;

    // Unit Under Test
    summator uut_inst (
        .a(a),
        .b(b),
        .c(c),
        .s(s),
        .h_c(h_c)
    );

    initial begin
        $dumpfile("summator_tb.vcd");
        $dumpvars(0, summator_tb);

        $display("Time\tA B C | S C_out");
        $display("------------------------");

        for (i = 0; i < 8; i = i + 1) begin
            {a, b, c} = i;
            #10;
            $display("%0t\t%b %b %b | %b   %b", $time, a, b, c, s, h_c);
        end

        $display("Test complete");
        $finish;
    end
endmodule

labs/lab_03/summator_tb.vcd
$date
	Sat Mar 21 18:52:17 2026
$end
$version
	Icarus Verilog
$end
$timescale
	1ns
$end
$scope module summator_tb $end
$var wire 1 ! s $end
$var wire 1 " h_c $end
$var reg 1 # a $end
$var reg 1 $ b $end
$var reg 1 % c $end
$var integer 32 & i [31:0] $end
$scope module uut_inst $end
$var wire 1 # a $end
$var wire 1 ' and1_out $end
$var wire 1 ( and2_out $end
$var wire 1 $ b $end
$var wire 1 % c $end
$var wire 1 " h_c $end
$var wire 1 ) or_out $end
$var wire 1 ! s $end
$var wire 1 * xor1_out $end
$var wire 1 + xor2_out $end
$upscope $end
$upscope $end
$enddefinitions $end
$comment Show the parameter values. $end
$dumpall
$end
#0
$dumpvars
0+
0*
0)
0(
0'
b0 &
0%
0$
0#
0"
0!
$end
#10
1!
1+
1%
b1 &
#20
1*
1!
1+
1$
0%
b10 &
#30
1"
1)
0!
0+
1(
1%
b11 &
#40
0"
0)
1!
1+
0(
1#
0$
0%
b100 &
#50
1"
1)
0!
0+
1(
1%
b101 &
#60
0*
1'
0!
0+
0(
1$
0%
b110 &
#70
1!
1+
1%
b111 &
#80
b1000 &
