labs/lab_6_GTK-Wawe/task_3/alu_8.v
module alu_8 (
    input  [7:0] A,
    input  [7:0] B,
    input  [1:0] select,
    output reg [7:0] Y
);

always @(*) begin
    case (select)

        // not (A + B)
        2'b00: Y = ~(A + B);

        // not (A * B)
        2'b01: Y = ~(A & B);

        // A + B + 1
        2'b10: Y = A + B + 8'd1;

        // (A + not B) + 1
        2'b11: Y = A + ~B + 8'd1;

    endcase
end

endmodule

labs/lab_06/task_3/alu_8_tb.v
module alu_8_tb;

reg  [7:0] A, B;
reg  [1:0] select;
wire [7:0] Y;

alu_8 dut (
    .A(A),
    .B(B),
    .select(select),
    .Y(Y)
);

initial begin
    $display("Time A B select Y");
    $display("Time    A    B  sel   Y");
    $monitor("%4t   %3d %3d  %b   %3d", $time, A, B, select, Y);

    A = 8'd10; B = 8'd3;

    select = 2'b00; #50;
    select = 2'b01; #50;
    select = 2'b10; #50;
    select = 2'b11; #50;

    A = 8'd25; B = 8'd7;

    select = 2'b00; #50;
    select = 2'b01; #50;
    select = 2'b10; #50;
    select = 2'b11; #50;

    #50 $finish;
end

initial begin
    $dumpfile("alu_8.vcd");
    $dumpvars(0, alu_8_tb);
end

endmodule

labs/lab_06/task_3/alu_8.vcd
$date
	Tue May 19 20:10:02 2026
$end
$version
	Icarus Verilog
$end
$timescale
	1s
$end
$scope module alu_8_tb $end
$var wire 8 ! Y [7:0] $end
$var reg 8 " A [7:0] $end
$var reg 8 # B [7:0] $end
$var reg 2 $ select [1:0] $end
$scope module dut $end
$var wire 8 % A [7:0] $end
$var wire 8 & B [7:0] $end
$var wire 2 ' select [1:0] $end
$var reg 8 ( Y [7:0] $end
$upscope $end
$upscope $end
$enddefinitions $end
$comment Show the parameter values. $end
$dumpall
$end
#0
$dumpvars
b11110010 (
b0 '
b11 &
b1010 %
b0 $
b11 #
b1010 "
b11110010 !
$end
#50
b11111101 !
b11111101 (
b1 $
b1 '
#100
b1110 !
b1110 (
b10 $
b10 '
#150
b111 !
b111 (
b11 $
b11 '
#200
b11011111 !
b11011111 (
b0 $
b0 '
b111 #
b111 &
b11001 "
b11001 %
#250
b11111110 !
b11111110 (
b1 $
b1 '
#300
b100001 !
b100001 (
b10 $
b10 '
#350
b10010 !
b10010 (
b11 $
b11 '
