labs/lab_04/cntSignal.v
/*
1. Реалізувати модуль cntSignal, який підраховує кількість одиниць на чотирьох входах та видає результат у двійковому коді.

| X1 | X2 | X3 | X4 | Y | Y2 | Y1 | Y0 |
| -- | -- | -- | -- | - | -- | -- | -- |
| 0  | 0  | 0  | 0  | 0 | 0  | 0  | 0  | 
| 0  | 0  | 0  | 1  | 1 | 0  | 0  | 1  | 0010₂ => Y = 1 -> 001₂
| 0  | 0  | 1  | 0  | 1 | 0  | 0  | 1  |
| 0  | 0  | 1  | 1  | 2 | 0  | 1  | 0  | 0011₂ => Y = 2 -> 010₂
| 0  | 1  | 0  | 0  | 1 | 0  | 0  | 1  |
| 0  | 1  | 0  | 1  | 2 | 0  | 1  | 0  |
| 0  | 1  | 1  | 0  | 2 | 0  | 1  | 0  |
| 0  | 1  | 1  | 1  | 3 | 0  | 1  | 1  |
| 1  | 0  | 0  | 0  | 1 | 0  | 0  | 1  |
| 1  | 0  | 0  | 1  | 2 | 0  | 1  | 0  |
| 1  | 0  | 1  | 0  | 2 | 0  | 1  | 0  |
| 1  | 0  | 1  | 1  | 3 | 0  | 1  | 1  |
| 1  | 1  | 0  | 0  | 2 | 0  | 1  | 0  |
| 1  | 1  | 0  | 1  | 3 | 0  | 1  | 1  |
| 1  | 1  | 1  | 0  | 3 | 0  | 1  | 1  |
| 1  | 1  | 1  | 1  | 4 | 1  | 0  | 0  |
*/

module cntSignal(
    input x1, input x2, input x3, input x4,
    output y2, output y1, output y0
);

assign {y2, y1, y0} = x1 + x2 + x3 + x4; // sum of input in binary form

endmodule

labs/lab_04/cntSignal_tb.v
`timescale 1ns/1ps

module cntSignal_tb;

reg x1, x2, x3, x4;
wire y2, y1, y0;

cntSignal uut (
    .x1(x1),
    .x2(x2),
    .x3(x3),
    .x4(x4),
    .y2(y2),
    .y1(y1),
    .y0(y0)
);

initial begin
    $dumpfile("cntSignal.vcd");
    $dumpvars(0, cntSignal_tb);

    $display("x1 x2 x3 x4 | y2 y1 y0");

    for (integer i = 0; i < 16; i = i + 1) begin
        {x1, x2, x3, x4} = i;
        #10;
        $display("%b  %b  %b  %b  |  %b  %b  %b", x1, x2, x3, x4, y2, y1, y0);
    end

    $finish;
end

endmodule

labs/lab_04/cntSignal.vcd
$date
	Tue Apr 07 17:16:27 2026
$end
$version
	Icarus Verilog
$end
$timescale
	1ps
$end
$scope module cntSignal_tb $end
$var wire 1 ! y2 $end
$var wire 1 " y1 $end
$var wire 1 # y0 $end
$var reg 1 $ x1 $end
$var reg 1 % x2 $end
$var reg 1 & x3 $end
$var reg 1 ' x4 $end
$scope module uut $end
$var wire 1 $ x1 $end
$var wire 1 % x2 $end
$var wire 1 & x3 $end
$var wire 1 ' x4 $end
$var wire 1 ! y2 $end
$var wire 1 " y1 $end
$var wire 1 # y0 $end
$upscope $end
$scope begin $ivl_for_loop0 $end
$var integer 32 ( i [31:0] $end
$upscope $end
$upscope $end
$enddefinitions $end
$comment Show the parameter values. $end
$dumpall
$end
#0
$dumpvars
b0 (
0'
0&
0%
0$
0#
0"
0!
$end
#10000
1#
1'
b1 (
#20000
1&
0'
b10 (
#30000
0#
1"
1'
b11 (
#40000
1#
0"
1%
0&
0'
b100 (
#50000
0#
1"
1'
b101 (
#60000
1&
0'
b110 (
#70000
1#
1'
b111 (
#80000
0"
1$
0%
0&
0'
b1000 (
#90000
0#
1"
1'
b1001 (
#100000
1&
0'
b1010 (
#110000
1#
1'
b1011 (
#120000
0#
1%
0&
0'
b1100 (
#130000
1#
1'
b1101 (
#140000
1&
0'
b1110 (
#150000
0#
0"
1!
1'
b1111 (
#160000
b10000 (
